diffuse_my_lyrics/__init__.py
diffuse_my_lyrics/lyrics_to_images.py
diffuse_my_lyrics/utils.py
diffuse_my_lyrics-0.0.2.dist-info/METADATA
diffuse_my_lyrics-0.0.2.dist-info/WHEEL
diffuse_my_lyrics-0.0.2.dist-info/top_level.txt
diffuse_my_lyrics-0.0.2.dist-info/RECORD
