Metadata-Version: 2.1
Name: diffuse-my-lyrics
Version: 0.0.2
Summary: A dummy project to generate images from song lyrics using Latent Stable Diffusion
Home-page: https://github.com/MichaelisTrofficus/diffuse_my_lyrics
Author: MTrofficus
Author-email: miguel.otero.pedrido.1993@gmail.com
Classifier: Programming Language :: Python :: 3
Classifier: License :: OSI Approved :: MIT License
Classifier: Operating System :: OS Independent
Requires-Python: >=3.7.0
Requires-Dist: diffusers (==0.2.4)
Requires-Dist: transformers (==4.24.0)
Requires-Dist: scipy
Requires-Dist: ftfy
